{
  "is_active": "Y",
  "id": "193",
  "pipeline_id": 9,
  "task_name": "testtuploadtogit",
  "task_description": "testtuploadtogit description",
  "task_type": "mysql_to_Mysql",
  "task_sequence": "56",
  "task": {
    "source": {
      "schema": "information_schema",
      "source_type": "mysql_read",
      "table_name": "tbl_user",
      "query": "select* from tbl_user",
      "chunk_size": 1000,
      "connection_name": "mysql connection",
      "select_columns": " "
    },
    "target": {
      "connection_name": "mysql connection",
      "target_type": "mysql_write",
      "operation": "create",
      "audit_columns": "active",
      "schema": "information_schema",
      "table_name": "tbl_user"
    },
    "data_quality_execution": {
      "pre_check_enable": "N",
      "post_check_enable": "N"
    }
  }
}